pass_pls.py
pass_pls-1.0.4.dist-info/LICENSE
pass_pls-1.0.4.dist-info/METADATA
pass_pls-1.0.4.dist-info/WHEEL
pass_pls-1.0.4.dist-info/entry_points.txt
pass_pls-1.0.4.dist-info/top_level.txt
pass_pls-1.0.4.dist-info/RECORD
